Metadata-Version: 1.1
Name: Flask-CKFinder3
Version: 0.1.1
Summary: Flask CKFinder3 connector
Home-page: https://gitlab.com/aristofor/flask-ckfinder3
Author: Aristofor Kolomb
Author-email: aristofor@gmail.com
License: MIT
Platform: UNKNOWN
Classifier: Development Status :: 4 - Beta
Classifier: Programming Language :: Python :: 3
Classifier: Environment :: Web Environment
Classifier: Framework :: Flask
Classifier: Topic :: Internet :: WWW/HTTP :: Site Management
Classifier: License :: OSI Approved :: MIT License
